sanic_attrs/__init__.py
sanic_attrs/doc.py
sanic_attrs/openapi.py
sanic_attrs/options.py
sanic_attrs/parser.py
sanic_attrs/response.py
sanic_attrs/serializer.py
sanic_attrs/swagger.py
sanic_attrs/validators.py
sanic_attrs/ui/favicon-16x16.png
sanic_attrs/ui/favicon-32x32.png
sanic_attrs/ui/index.html
sanic_attrs/ui/oauth2-redirect.html
sanic_attrs-0.2.1.dist-info/METADATA
sanic_attrs-0.2.1.dist-info/RECORD
sanic_attrs-0.2.1.dist-info/WHEEL
sanic_attrs-0.2.1.dist-info/top_level.txt
